{
  "title": "Vincent",
  "date": "2026-04-03",
  "cover": "IMG_5218.jpg",
"photos": [
    { "file": "IMG_5218.jpg", "alt": "Vincent" },
    { "file": "IMG_4911.jpg", "alt": "Vincent" },
    { "file": "IMG_4917.jpg", "alt": "Vincent" },
    { "file": "IMG_4939.jpg", "alt": "Vincent" },
    { "file": "IMG_4947.jpg", "alt": "Vincent" },
    { "file": "IMG_4957.jpg", "alt": "Vincent" },
    { "file": "IMG_4960.jpg", "alt": "Vincent" },
    { "file": "IMG_4968.jpg", "alt": "Vincent" },
    { "file": "IMG_4973.jpg", "alt": "Vincent" },
    { "file": "IMG_4978.jpg", "alt": "Vincent" },
    { "file": "IMG_4988.jpg", "alt": "Vincent" },
    { "file": "IMG_4993.jpg", "alt": "Vincent" },
    { "file": "IMG_5008.jpg", "alt": "Vincent" },
    { "file": "IMG_5015.jpg", "alt": "Vincent" },
    { "file": "IMG_5021.jpg", "alt": "Vincent" },
    { "file": "IMG_5048.jpg", "alt": "Vincent" },
    { "file": "IMG_5051.jpg", "alt": "Vincent" },
    { "file": "IMG_5056.jpg", "alt": "Vincent" },
    { "file": "IMG_5063.jpg", "alt": "Vincent" },
    { "file": "IMG_5067.jpg", "alt": "Vincent" },
    { "file": "IMG_5073.jpg", "alt": "Vincent" },
    { "file": "IMG_5080.jpg", "alt": "Vincent" },
    { "file": "IMG_5082.jpg", "alt": "Vincent" },
    { "file": "IMG_5092.jpg", "alt": "Vincent" },
    { "file": "IMG_5097.jpg", "alt": "Vincent" },
    { "file": "IMG_5128.jpg", "alt": "Vincent" },
    { "file": "IMG_5133.jpg", "alt": "Vincent" },
    { "file": "IMG_5140.jpg", "alt": "Vincent" },
    { "file": "IMG_5142.jpg", "alt": "Vincent" },
    { "file": "IMG_5149.jpg", "alt": "Vincent" },
    { "file": "IMG_5154.jpg", "alt": "Vincent" },
    { "file": "IMG_5211.jpg", "alt": "Vincent" },
    { "file": "IMG_5242.jpg", "alt": "Vincent" }
  ]
}
